{"accounts":[{"account":{"active":false,"allocationHistory":[],"balance":"0","identity":{"address":"N\u0000sourcecred\u0000core\u0000IDENTITY\u0000yT05wCVktx1RjJDGCEfV4w\u0000","aliases":[{"address":"N\u0000sourcecred\u0000github\u0000USERLIKE\u0000USER\u0000jlwaugh\u0000","description":"github/[@jlwaugh](https://github.com/jlwaugh)"}],"id":"yT05wCVktx1RjJDGCEfV4w","name":"jlwaugh","subtype":"USER"},"mergedIdentityIds":["yT05wCVktx1RjJDGCEfV4w"],"paid":"0","payoutAddresses":{}},"cred":[6.904106594584004,1.0958904923777797],"totalCred":7.999997086961784},{"account":{"active":false,"allocationHistory":[],"balance":"0","identity":{"address":"N\u0000sourcecred\u0000core\u0000IDENTITY\u0000jXn5cvf2HyOHBWfJuAPnHg\u0000","aliases":[{"address":"N\u0000sourcecred\u0000github\u0000USERLIKE\u0000USER\u0000gitbook-bot\u0000","description":"github/[@gitbook-bot](https://github.com/gitbook-bot)"}],"id":"jXn5cvf2HyOHBWfJuAPnHg","name":"gitbook-bot","subtype":"USER"},"mergedIdentityIds":["jXn5cvf2HyOHBWfJuAPnHg"],"paid":"0","payoutAddresses":{}},"cred":[5.817305483550645e-13,1.2033093281866984e-13],"totalCred":7.020614811737344e-13},{"account":{"active":true,"allocationHistory":[],"balance":"0","identity":{"address":"N\u0000sourcecred\u0000core\u0000IDENTITY\u0000IJDOjfP8w0cvqyrGBwkWGw\u0000","aliases":[],"id":"IJDOjfP8w0cvqyrGBwkWGw","name":"SourceCred","subtype":"PROJECT"},"mergedIdentityIds":["IJDOjfP8w0cvqyrGBwkWGw"],"paid":"0","payoutAddresses":{}},"cred":[3.0254198395924933e-38,3.0254198395924933e-38],"totalCred":6.050839679184987e-38}],"intervals":[{"endTimeMs":1626566400000,"startTimeMs":1625961600000},{"endTimeMs":1627171200000,"startTimeMs":1626566400000}],"unclaimedAliases":[]}